{"disruptor": ["Disruptor", "https://gamepedia.cursecdn.com/dota2_ru_gamepedia/2/2f/Dis_spawn_01_ru.mp3"], "\u0432\u043b\u0430\u0434\u044b\u043a\u0430 \u0431\u0443\u0440\u044c \u0433\u0440\u044f\u0434\u0451\u0442": ["Disruptor", "https://gamepedia.cursecdn.com/dota2_ru_gamepedia/8/89/Dis_spawn_02_ru.mp3"], "\u0431\u0435\u0437\u043e\u0431\u043b\u0430\u0447\u043d\u043e\u0435 \u043d\u0435\u0431\u043e \u0437\u0430\u0442\u044f\u043d\u0443\u043b\u0438 \u0442\u0443\u0447\u0438": ["Disruptor", "https://gamepedia.cursecdn.com/dota2_ru_gamepedia/d/d0/Dis_spawn_03_ru.mp3"], "\u0432\u043e\u0439\u043d\u0430 \u0435\u0441\u0442\u044c \u0443\u0440\u0430\u0432\u043d\u0435\u043d\u0438\u0435 \u0430 \u0441\u043c\u0435\u0440\u0442\u044c \u0435\u0433\u043e \u0440\u0435\u0448\u0435\u043d\u0438\u0435": ["Disruptor", "https://gamepedia.cursecdn.com/dota2_ru_gamepedia/d/dc/Dis_spawn_04_ru.mp3"], "\u0438 \u0433\u0440\u044f\u043d\u0443\u043b \u0433\u0440\u043e\u043c \u0441\u0440\u0430\u0436\u0435\u043d\u0438\u044f": ["Disruptor", "https://gamepedia.cursecdn.com/dota2_ru_gamepedia/8/80/Dis_begin_01_ru.mp3"], "\u043c\u043e\u0439 \u043f\u0443\u0442\u044c \u043b\u0435\u0436\u0438\u0442 \u0438\u0437 \u043d\u0430\u0433\u043e\u0440\u0438\u0439 \u0434\u0440\u0443\u0443\u0434\u0430": ["Disruptor", "https://gamepedia.cursecdn.com/dota2_ru_gamepedia/3/33/Dis_move_10_ru.mp3"], "\u0434\u043e\u0433\u043e\u043d\u044e \u0438 \u0440\u0430\u0441\u0442\u043e\u043f\u0447\u0443": ["Disruptor", "https://gamepedia.cursecdn.com/dota2_ru_gamepedia/3/3d/Dis_cast_01_ru.mp3"], "\u0433\u0440\u043e\u0437\u0430 \u043f\u0440\u0438\u0431\u043b\u0438\u0436\u0430\u0435\u0442\u0441\u044f": ["Disruptor", "https://gamepedia.cursecdn.com/dota2_ru_gamepedia/0/00/Dis_cast_03_ru.mp3"], "\u043a\u0430\u043a\u0438\u0435 \u0433\u0440\u043e\u0437\u044b \u044f \u0443\u0441\u0442\u0440\u043e\u044e": ["Disruptor", "https://gamepedia.cursecdn.com/dota2_ru_gamepedia/0/0d/Dis_levelup_03_ru.mp3"], "\u0438\u0442\u0430\u043a \u044f \u0441\u043e\u043a\u0440\u0443\u0448\u0438\u043b \u043f\u0440\u043e\u0442\u0438\u0432\u043d\u0438\u043a\u0430": ["Disruptor", "https://gamepedia.cursecdn.com/dota2_ru_gamepedia/e/e6/Dis_win_03_ru.mp3"], "\u044f \u043e\u0431\u0440\u0443\u0448\u0443 \u0433\u0440\u043e\u0437\u0443 \u043d\u0430 \u0433\u043e\u043b\u043e\u0432\u044b \u0441\u0432\u043e\u0438\u0445 \u0432\u0440\u0430\u0433\u043e\u0432": ["Disruptor", "https://gamepedia.cursecdn.com/dota2_ru_gamepedia/3/39/Dis_rare_01_ru.mp3"], "\u043c\u043e\u0438 \u0443\u043c\u0435\u043d\u0438\u044f \u0432\u0441\u0435 \u0440\u0430\u0441\u0442\u0443\u0442": ["Disruptor", "https://gamepedia.cursecdn.com/dota2_ru_gamepedia/8/84/Dis_levelup_05_ru.mp3"], "\u0431\u044d \u044d \u0433\u0445": ["Disruptor", "https://gamepedia.cursecdn.com/dota2_ru_gamepedia/d/d0/Dis_anger_06_ru.mp3"], "\u043f\u0440\u043e\u0433\u043d\u043e\u0437 \u043d\u0430 \u0431\u0438\u0442\u0432\u0443 \u0441\u0430\u043c\u044b\u0439 \u0431\u043b\u0430\u0433\u043e\u043f\u0440\u0438\u044f\u0442\u043d\u044b\u0439 \u0434\u0435\u043b\u043e \u0432 \u0448\u043b\u044f\u043f\u0435": ["Disruptor", "https://gamepedia.cursecdn.com/dota2_ru_gamepedia/7/70/Dis_inthebag_01_ru.mp3"], "\u043e\u0436\u0438\u0434\u0430\u0435\u0442\u0441\u044f \u0434\u043e\u0436\u0434\u044c \u043a\u0440\u043e\u0432\u0438": ["Disruptor", "https://gamepedia.cursecdn.com/dota2_ru_gamepedia/6/6c/Dis_begin_02_ru.mp3"], "\u0434\u0430": ["Disruptor", "https://gamepedia.cursecdn.com/dota2_ru_gamepedia/8/8b/Dis_move_01_ru.mp3"], "\u0431\u044b\u0441\u0442\u0440\u0435\u0435 \u0432\u0435\u0442\u0440\u0430": ["Disruptor", "https://gamepedia.cursecdn.com/dota2_ru_gamepedia/5/56/Dis_move_03_ru.mp3"], "\u0432\u043f\u0435\u0440\u0451\u0434": ["Disruptor", "https://gamepedia.cursecdn.com/dota2_ru_gamepedia/b/bb/Dis_move_04_ru.mp3"], "\u043a \u0446\u0435\u043b\u0438": ["Disruptor", "https://gamepedia.cursecdn.com/dota2_ru_gamepedia/8/82/Dis_move_05_ru.mp3"], "\u0441\u044e\u0434\u0430": ["Disruptor", "https://gamepedia.cursecdn.com/dota2_ru_gamepedia/0/07/Dis_move_06_ru.mp3"], "\u044f\u0440\u043e\u0441\u0442\u044c \u0437\u0430\u043a\u0438\u043f\u0430\u0435\u0442": ["Disruptor", "https://gamepedia.cursecdn.com/dota2_ru_gamepedia/f/f5/Dis_move_07_ru.mp3"], "\u0431\u044b\u0441\u0442\u0440\u0435\u0435": ["Disruptor", "https://gamepedia.cursecdn.com/dota2_ru_gamepedia/6/68/Dis_move_08_ru.mp3"], "\u0443\u0436\u0435 \u0438\u0434\u0443": ["Disruptor", "https://gamepedia.cursecdn.com/dota2_ru_gamepedia/6/6e/Dis_move_09_ru.mp3"], "stryghor \u0432 \u043f\u0443\u0442\u0438": ["Disruptor", "https://gamepedia.cursecdn.com/dota2_ru_gamepedia/b/be/Dis_move_11_ru.mp3"], "\u0433\u0440\u043e\u043c\u043e\u0433\u043b\u0430\u0441\u043d\u043e": ["Disruptor", "https://gamepedia.cursecdn.com/dota2_ru_gamepedia/8/85/Dis_move_12_ru.mp3"], "\u0432 \u0430\u0442\u0430\u043a\u0443": ["Disruptor", "https://gamepedia.cursecdn.com/dota2_ru_gamepedia/3/3d/Dis_attack_01_ru.mp3"], "\u044f \u043d\u0435 \u0431\u0443\u0434\u0443 \u0441\u0434\u0435\u0440\u0436\u0438\u0432\u0430\u0442\u044c\u0441\u044f": ["Disruptor", "https://gamepedia.cursecdn.com/dota2_ru_gamepedia/b/b7/Dis_attack_02_ru.mp3"], "\u0441\u0438\u0441\u0442\u0435\u043c\u0430 \u0430\u0434\u0430\u043f\u0442\u0438\u0440\u0443\u0435\u0442\u0441\u044f": ["Disruptor", "https://gamepedia.cursecdn.com/dota2_ru_gamepedia/5/5c/Dis_attack_03_ru.mp3"], "\u0441\u043e\u043a\u0440\u043e\u0432\u0435\u043d\u043d\u044b\u0435 \u0437\u043d\u0430\u043d\u0438\u044f": ["Disruptor", "https://gamepedia.cursecdn.com/dota2_ru_gamepedia/5/5c/Dis_attack_04_ru.mp3"], "\u043f\u043e\u043b\u0443\u0447\u0430\u0439": ["Disruptor", "https://gamepedia.cursecdn.com/dota2_ru_gamepedia/4/4d/Dis_attack_05_ru.mp3"], "\u0443\u043f\u0440\u0430\u0432\u043b\u044f\u0435\u043c\u043e\u0435 \u0431\u0435\u0437\u0443\u043c\u0438\u0435": ["Disruptor", "https://gamepedia.cursecdn.com/dota2_ru_gamepedia/5/5b/Dis_attack_06_ru.mp3"], "\u0436\u0430\u043b\u043a\u0430\u044f \u0442\u0432\u0430\u0440\u044c": ["Disruptor", "https://gamepedia.cursecdn.com/dota2_ru_gamepedia/b/b0/Dis_attack_07_ru.mp3"], "\u0440\u0430\u0437\u043e\u0439\u0434\u0438\u0441\u044c": ["Disruptor", "https://gamepedia.cursecdn.com/dota2_ru_gamepedia/a/af/Dis_attack_08_ru.mp3"], "\u044f \u0431\u044b\u0441\u0442\u0440\u043e": ["Disruptor", "https://gamepedia.cursecdn.com/dota2_ru_gamepedia/0/0c/Dis_attack_09_ru.mp3"], "\u043a\u0430\u043a \u0443\u0440\u0430\u0433\u0430\u043d": ["Disruptor", "https://gamepedia.cursecdn.com/dota2_ru_gamepedia/b/be/Dis_attack_10_ru.mp3"], "\u043d\u0435 \u0443\u0439\u0434\u0451\u0448\u044c": ["Disruptor", "https://gamepedia.cursecdn.com/dota2_ru_gamepedia/f/f3/Dis_cast_02_ru.mp3"], "\u0441\u0438\u043b\u0430 \u0441\u0442\u0438\u0445\u0438\u0439": ["Disruptor", "https://gamepedia.cursecdn.com/dota2_ru_gamepedia/c/ce/Dis_thunderstrike_01_ru.mp3"], "\u0440\u0430\u0437\u0440\u0430\u0437\u0438 \u0442\u0435\u0431\u044f \u0433\u0440\u043e\u043c": ["Disruptor", "https://gamepedia.cursecdn.com/dota2_ru_gamepedia/5/5c/Dis_thunderstrike_02_ru.mp3"], "\u0433\u0440\u043e\u043c \u0438 \u043c\u043e\u043b\u043d\u0438\u044f": ["Disruptor", "https://gamepedia.cursecdn.com/dota2_ru_gamepedia/d/df/Dis_thunderstrike_03_ru.mp3"], "\u0433\u0440\u043e\u0437\u043e\u0432\u044b\u0435 \u0442\u0443\u0447\u0438": ["Disruptor", "https://gamepedia.cursecdn.com/dota2_ru_gamepedia/8/83/Dis_thunderstrike_04_ru.mp3"], "\u0441\u0442\u0443\u043f\u0430\u0439 \u043e\u0431\u0440\u0430\u0442\u043d\u043e": ["Disruptor", "https://gamepedia.cursecdn.com/dota2_ru_gamepedia/b/b1/Dis_glimpse_01_ru.mp3"], "\u043a\u0443\u0434\u0430 \u0442\u0430\u043a \u0448\u0443\u0441\u0442\u0440\u043e": ["Disruptor", "https://gamepedia.cursecdn.com/dota2_ru_gamepedia/f/fd/Dis_glimpse_04_ru.mp3"], "\u043f\u0440\u0438\u0432\u0435\u0442 \u0438\u0437 \u043f\u0440\u043e\u0448\u043b\u043e\u0433\u043e": ["Disruptor", "https://gamepedia.cursecdn.com/dota2_ru_gamepedia/f/ff/Dis_glimpse_03_ru.mp3"], "glimpse": ["Disruptor", "https://gamepedia.cursecdn.com/dota2_ru_gamepedia/e/e1/Dis_glimpse_05_ru.mp3"], "\u0436\u0438\u0432\u043e\u0442\u043d\u044b\u0445 \u0432 \u0437\u0430\u0433\u043e\u043d": ["Disruptor", "https://gamepedia.cursecdn.com/dota2_ru_gamepedia/a/a4/Dis_kineticfield_03_ru.mp3"], "\u043d\u0435\u043f\u0440\u0435\u043e\u0434\u043e\u043b\u0438\u043c\u044b\u0439 \u0431\u0430\u0440\u044c\u0435\u0440": ["Disruptor", "https://gamepedia.cursecdn.com/dota2_ru_gamepedia/f/f1/Dis_kineticfield_04_ru.mp3"], "\u043d\u0438 \u0448\u0430\u0433\u0430 \u0434\u0430\u043b\u044c\u0448\u0435": ["Disruptor", "https://gamepedia.cursecdn.com/dota2_ru_gamepedia/d/d3/Dis_kineticfield_05_ru.mp3"], "\u043f\u043e\u043b\u044e\u0448\u043a\u043e \u043f\u043e\u043b\u0435": ["Disruptor", "https://gamepedia.cursecdn.com/dota2_ru_gamepedia/7/7f/Dis_kineticfield_01_ru.mp3"], "\u0438 \u043e\u0434\u0438\u043d \u0432 \u043f\u043e\u043b\u0435 \u0432\u043e\u0438\u043d": ["Disruptor", "https://gamepedia.cursecdn.com/dota2_ru_gamepedia/e/ea/Dis_kineticfield_02_ru.mp3"], "static storm": ["Disruptor", "https://gamepedia.cursecdn.com/dota2_ru_gamepedia/5/5e/Dis_staticstorm_01_ru.mp3"], "\u0442\u043e\u043a": ["Disruptor", "https://gamepedia.cursecdn.com/dota2_ru_gamepedia/c/ca/Dis_staticstorm_02_ru.mp3"], "\u0440\u0430\u0437\u0440\u044f\u0434": ["Disruptor", "https://gamepedia.cursecdn.com/dota2_ru_gamepedia/8/8f/Dis_staticstorm_04_ru.mp3"], "\u043f\u043e\u043c\u0435\u0445\u0438": ["Disruptor", "https://gamepedia.cursecdn.com/dota2_ru_gamepedia/3/3d/Dis_staticstorm_05_ru.mp3"], "\u044f\u0440\u043e \u0437\u0430\u0440\u044f\u0436\u0430\u044e\u0441\u044c": ["Disruptor", "https://gamepedia.cursecdn.com/dota2_ru_gamepedia/0/0a/Dis_staticstorm_06_ru.mp3"], "\u0432\u043e\u0442 \u0442\u0435\u0431\u0435 \u0437\u0430\u0440\u044f\u0434": ["Disruptor", "https://gamepedia.cursecdn.com/dota2_ru_gamepedia/c/cb/Dis_staticstorm_03_ru.mp3"], "\u044f \u0443\u0437\u043d\u0430\u043b \u043a\u043e\u0435 \u0447\u0442\u043e \u043d\u043e\u0432\u043e\u0435": ["Disruptor", "https://gamepedia.cursecdn.com/dota2_ru_gamepedia/0/09/Dis_levelup_01_ru.mp3"], "\u043f\u0440\u0438\u0431\u044b\u043b\u043e \u0437\u043d\u0430\u043d\u0438\u0435 \u0438 \u0441\u0438\u043b\u044b": ["Disruptor", "https://gamepedia.cursecdn.com/dota2_ru_gamepedia/3/30/Dis_levelup_02_ru.mp3"], "\u044f \u043f\u043e\u0434\u0437\u0430\u0440\u044f\u0434\u0438\u043b\u0441\u044f": ["Disruptor", "https://gamepedia.cursecdn.com/dota2_ru_gamepedia/5/51/Dis_levelup_04_ru.mp3"], "\u043c\u0435\u043d\u044f \u043c\u0447\u0438\u0442 \u043f\u043e\u043f\u0443\u0442\u043d\u044b\u0439 \u0432\u0435\u0442\u0435\u0440": ["Disruptor", "https://gamepedia.cursecdn.com/dota2_ru_gamepedia/5/56/Dis_levelup_06_ru.mp3"], "\u043d\u0430 \u043a\u0440\u044b\u043b\u044c\u044f\u0445 \u0431\u0443\u0440\u0438": ["Disruptor", "https://gamepedia.cursecdn.com/dota2_ru_gamepedia/7/7d/Dis_levelup_07_ru.mp3"], "\u0430 \u0445\u0430 \u0445\u0430 \u0445\u0430 \u0445\u0430 \u0445\u0430": ["Disruptor", "https://gamepedia.cursecdn.com/dota2_ru_gamepedia/3/3c/Dis_levelup_08_ru.mp3"], "\u0430 \u0445\u0430 \u0445\u0430 \u0445\u0430 \u0445\u0430 \u0445\u0430 \u0445\u0430 \u0445\u0430": ["Disruptor", "https://gamepedia.cursecdn.com/dota2_ru_gamepedia/e/e6/Dis_levelup_09_ru.mp3"], "\u0437\u043d\u0430\u043d\u0438\u044f \u0434\u0440\u0435\u0432\u043d\u0438\u0445 \u043e\u0431\u0440\u0435\u0442\u0435\u043d\u044b \u0441\u043d\u043e\u0432\u0430": ["Disruptor", "https://gamepedia.cursecdn.com/dota2_ru_gamepedia/c/cc/Dis_levelup_10_ru.mp3"], "\u0438\u0434\u0451\u0442 \u0430\u0442\u043c\u043e\u0441\u0444\u0435\u0440\u043d\u044b\u0439 \u0444\u0440\u043e\u043d\u0442": ["Disruptor", "https://gamepedia.cursecdn.com/dota2_ru_gamepedia/2/28/Dis_levelup_11_ru.mp3"], "\u044f \u0442\u0435\u0431\u044f \u043f\u0435\u0440\u0435\u0431\u0438\u043b": ["Disruptor", "https://gamepedia.cursecdn.com/dota2_ru_gamepedia/d/d4/Dis_kill_01_ru.mp3"], "\u0442\u0435\u0431\u044f \u043a\u0430\u0436\u0435\u0442\u0441\u044f \u043f\u0440\u043e\u0434\u0443\u043b\u043e": ["Disruptor", "https://gamepedia.cursecdn.com/dota2_ru_gamepedia/b/ba/Dis_kill_02_ru.mp3"], "\u043e\u0442\u0434\u043e\u0445\u043d\u0438 \u0432 \u0433\u0440\u043e\u0431\u0443": ["Disruptor", "https://gamepedia.cursecdn.com/dota2_ru_gamepedia/d/d6/Dis_kill_03_ru.mp3"], "\u0438\u0437 \u0442\u0435\u0431\u044f \u043b\u043e\u043f\u0443\u0445 \u0432\u044b\u0440\u0430\u0441\u0442\u0435\u0442": ["Disruptor", "https://gamepedia.cursecdn.com/dota2_ru_gamepedia/a/af/Dis_kill_04_ru.mp3"], "\u043e\u0442\u043f\u0440\u0430\u0432\u043b\u044f\u0439\u0441\u044f \u0442\u0443\u0434\u0430 \u0433\u0434\u0435 \u0432\u0435\u0442\u0435\u0440 \u043d\u0435 \u0434\u0443\u0435\u0442": ["Disruptor", "https://gamepedia.cursecdn.com/dota2_ru_gamepedia/a/a7/Dis_kill_05_ru.mp3"], "\u043e\u0434\u043d\u0438\u043c \u0432\u0440\u0430\u0433\u043e\u043c \u043c\u0435\u043d\u044c\u0448\u0435": ["Disruptor", "https://gamepedia.cursecdn.com/dota2_ru_gamepedia/0/03/Dis_kill_06_ru.mp3"], "\u043d\u0435 \u0441\u043e\u0439\u0442\u0438 \u0442\u0435\u0431\u0435 \u0441 \u044d\u0442\u043e\u0433\u043e \u043c\u0435\u0441\u0442\u0430": ["Disruptor", "https://gamepedia.cursecdn.com/dota2_ru_gamepedia/4/49/Dis_kill_07_ru.mp3"], "\u0432\u043a\u043b\u044e\u0447\u0430\u044e \u0443\u0431\u043e\u0439\u043d\u044b\u0439 \u0440\u0435\u0436\u0438\u043c": ["Disruptor", "https://gamepedia.cursecdn.com/dota2_ru_gamepedia/c/ca/Dis_kill_08_ru.mp3"], "\u043a\u043e\u043c\u0443 \u0433\u0440\u043e\u0437\u0430 \u043a\u043e\u043c\u0443 \u0433\u0440\u043e\u0431": ["Disruptor", "https://gamepedia.cursecdn.com/dota2_ru_gamepedia/5/56/Dis_kill_09_ru.mp3"], "\u0437\u0430\u0442\u043e\u043f\u0442\u0430\u043b\u0438 \u0442\u0435\u0431\u044f": ["Disruptor", "https://gamepedia.cursecdn.com/dota2_ru_gamepedia/b/ba/Dis_kill_11_ru.mp3"], "\u0445\u0430 \u0445\u0430 \u0445\u0430 \u0445\u0430 \u0445\u0430 \u0445\u0430": ["Disruptor", "https://gamepedia.cursecdn.com/dota2_ru_gamepedia/0/05/Dis_laugh_05_ru.mp3"], "\u0445\u043e \u0445\u043e \u0445\u043e \u0445\u043e \u0445\u043e \u0445\u043e": ["Disruptor", "https://gamepedia.cursecdn.com/dota2_ru_gamepedia/c/c3/Dis_kill_13_ru.mp3"], "\u0445\u0435 \u0445\u0435": ["Disruptor", "https://gamepedia.cursecdn.com/dota2_ru_gamepedia/a/a5/Dis_laugh_01_ru.mp3"], "\u0445\u043e \u0445\u043e": ["Disruptor", "https://gamepedia.cursecdn.com/dota2_ru_gamepedia/7/7c/Dis_laugh_02_ru.mp3"], "\u0445\u0435 \u0445\u0435 \u0445\u0430": ["Disruptor", "https://gamepedia.cursecdn.com/dota2_ru_gamepedia/0/07/Dis_laugh_03_ru.mp3"], "\u0430 \u0445\u0430 \u0445\u0430 \u0445\u0430 \u0445\u0430": ["Disruptor", "https://gamepedia.cursecdn.com/dota2_ru_gamepedia/f/fb/Dis_laugh_04_ru.mp3"], "\u0445\u0430 \u0445\u0430 \u0445\u0430 \u0445\u0430 \u0445\u0430 \u0445\u0430 \u0445\u0430": ["Disruptor", "https://gamepedia.cursecdn.com/dota2_ru_gamepedia/0/05/Dis_laugh_05_ru.mp3"], "\u043e\u0445 \u0445\u043e \u0445\u0430 \u0445\u0430 \u0445\u0430 \u0445\u0430": ["Disruptor", "https://gamepedia.cursecdn.com/dota2_ru_gamepedia/5/53/Dis_laugh_07_ru.mp3"], "\u043a\u0430\u043c\u0435\u043d\u043d\u044b\u0439 \u0431\u043e\u043b\u0432\u0430\u043d": ["Disruptor", "https://gamepedia.cursecdn.com/dota2_ru_gamepedia/4/4b/Dis_rival_01_ru.mp3"], "\u043e \u043c\u0451\u0440\u0442\u0432\u044b\u0445 \u043c\u043e\u0436\u043d\u043e \u0438 \u043f\u043b\u043e\u0445\u043e": ["Disruptor", "https://gamepedia.cursecdn.com/dota2_ru_gamepedia/7/79/Dis_rival_02_ru.mp3"], "\u0441\u043a\u0443\u043a\u0430 \u0441\u043c\u0435\u0440\u0442\u043d\u0430\u044f \u0434\u0430 \u0438 \u0442\u043e\u043b\u044c\u043a\u043e": ["Disruptor", "https://gamepedia.cursecdn.com/dota2_ru_gamepedia/7/76/Dis_rival_03_ru.mp3"], "\u043d\u0435\u043c\u043d\u043e\u0433\u043e \u0444\u0430\u043d\u0442\u0430\u0437\u0438\u0438 \u0438 \u0446\u0435\u043b\u0438\u0442\u0435\u043b\u044c\u043d\u0430\u044f \u0441\u0438\u043b\u0430": ["Disruptor", "https://gamepedia.cursecdn.com/dota2_ru_gamepedia/c/c0/Dis_rival_04_ru.mp3"], "\u043d\u0438\u0447\u0435\u0433\u043e \u043d\u0435 \u043f\u043e\u0434\u0435\u043b\u0430\u0435\u0448\u044c \u0441\u043e\u0440\u043e\u0434\u0438\u0447": ["Disruptor", "https://gamepedia.cursecdn.com/dota2_ru_gamepedia/3/3d/Dis_rival_05_ru.mp3"], "axe \u0442\u0435\u0431\u044f \u0432 \u0434\u0435\u0442\u0441\u0442\u0432\u0435 \u043d\u0435 \u0440\u043e\u043d\u044f\u043b\u0438 \u043d\u0430 \u0433\u043e\u043b\u043e\u0432\u0443": ["Disruptor", "https://gamepedia.cursecdn.com/dota2_ru_gamepedia/f/f7/Dis_rival_06_ru.mp3"], "axe \u0442\u044b \u0438 \u0440\u0430\u043d\u044c\u0448\u0435 \u043d\u0435 \u0431\u044b\u043b \u0448\u0443\u0441\u0442\u0440\u044b\u043c \u043f\u043e\u043b\u0435\u0436\u0438 \u0442\u0435\u043f\u0435\u0440\u044c": ["Disruptor", "https://gamepedia.cursecdn.com/dota2_ru_gamepedia/c/c6/Dis_rival_07_ru.mp3"], "warlock \u043d\u0430\u0448 \u043d\u0430\u0440\u043e\u0434 \u0432\u043d\u0435\u0441\u0451\u0442 \u0442\u0435\u0431\u044f \u0432 \u043a\u043d\u0438\u0433\u0438 \u043f\u0440\u0435\u0434\u043a\u043e\u0432": ["Disruptor", "https://gamepedia.cursecdn.com/dota2_ru_gamepedia/6/67/Dis_rival_08_ru.mp3"], "\u0442\u044b \u0437\u043d\u0430\u043b \u0431\u043e\u043b\u044c\u0448\u0435 \u0432\u0441\u0435\u0445 \u043d\u0430\u0441 warlock \u0438 \u0441\u0438\u043b\u044c\u043d\u0435\u0435 \u0432\u0441\u0435\u0445 \u0437\u0430\u0431\u043b\u0443\u0436\u0434\u0430\u043b\u0441\u044f": ["Disruptor", "https://gamepedia.cursecdn.com/dota2_ru_gamepedia/2/25/Dis_rival_09_ru.mp3"], "warlock \u043e \u0447\u0451\u043c \u0433\u043e\u0432\u043e\u0440\u0438\u0442 \u0442\u0432\u043e\u044f \u043a\u043d\u0438\u0433\u0430": ["Disruptor", "https://gamepedia.cursecdn.com/dota2_ru_gamepedia/f/f0/Dis_rival_10_ru.mp3"], "warlock \u0442\u0432\u043e\u044f \u043a\u043d\u0438\u0433\u0430 \u0443\u043a\u0440\u0430\u0441\u0438\u0442 \u043c\u043e\u0451 \u0441\u043e\u0431\u0440\u0430\u043d\u0438\u0435": ["Disruptor", "https://gamepedia.cursecdn.com/dota2_ru_gamepedia/a/aa/Dis_rival_11_ru.mp3"], "chen \u043c\u043e\u0435\u0433\u043e \u0441\u043a\u0430\u043a\u0443\u043d\u0430 \u0442\u044b \u043d\u0435 \u0437\u0430\u043a\u043e\u043b\u0434\u0443\u0435\u0448\u044c": ["Disruptor", "https://gamepedia.cursecdn.com/dota2_ru_gamepedia/a/a0/Dis_rival_12_ru.mp3"], "\u0434\u043e\u0445\u043b\u0430\u044f \u043b\u043e\u0448\u0430\u0434\u044c \u0438 \u0434\u043e\u0445\u043b\u044b\u0439 \u0432\u0441\u0430\u0434\u043d\u0438\u043a": ["Disruptor", "https://gamepedia.cursecdn.com/dota2_ru_gamepedia/4/42/Dis_rival_13_ru.mp3"], "\u0434\u0443\u0440\u0430\u043a\u0430 \u0447\u0442\u043e \u0433\u043e\u0440\u0431\u0430\u0442\u043e\u0433\u043e \u043c\u043e\u0433\u0438\u043b\u0430 \u0438\u0441\u043f\u0440\u0430\u0432\u0438\u0442": ["Disruptor", "https://gamepedia.cursecdn.com/dota2_ru_gamepedia/8/8e/Dis_rival_14_ru.mp3"], "\u0445\u0438\u0442\u0440\u044b\u0439 \u043d\u0430\u0440\u043e\u0434\u0438\u0448\u043a\u0430 \u0430 \u0443\u043c\u0438\u0440\u0430\u044e\u0442 \u043a\u0430\u043a \u0432\u0441\u0435": ["Disruptor", "https://gamepedia.cursecdn.com/dota2_ru_gamepedia/6/6f/Dis_rival_15_ru.mp3"], "\u0440\u043e\u0441\u0442\u043e\u043c \u043d\u0435 \u0432\u044b\u0448\u0435\u043b": ["Disruptor", "https://gamepedia.cursecdn.com/dota2_ru_gamepedia/b/b5/Dis_rival_16_ru.mp3"], "\u043c\u0430\u043b\u043e \u0440\u0430\u0437\u0434\u0443\u0442\u044c \u0431\u0443\u0440\u044e \u043d\u0430\u0434\u043e \u0443\u043c\u0435\u0442\u044c \u0437\u0430\u0449\u0438\u0449\u0430\u0442\u044c\u0441\u044f": ["Disruptor", "https://gamepedia.cursecdn.com/dota2_ru_gamepedia/2/2a/Dis_rival_17_ru.mp3"], "\u0433\u0440\u043e\u043c \u0430\u043f\u043b\u043e\u0434\u0438\u0441\u043c\u0435\u043d\u0442\u043e\u0432 \u0442\u0435\u0431\u0435 \u043d\u0430 \u0433\u043e\u043b\u043e\u0432\u0443": ["Disruptor", "https://gamepedia.cursecdn.com/dota2_ru_gamepedia/f/f6/Dis_rival_18_ru.mp3"], "\u0432\u043f\u0440\u043e\u0447\u0435\u043c \u0441 \u043c\u043e\u043b\u043d\u0438\u0435\u0439 \u0442\u044b \u0443\u043f\u0440\u0430\u0432\u043b\u044f\u0435\u0448\u044c\u0441\u044f \u043d\u0435\u043f\u043b\u043e\u0445\u043e": ["Disruptor", "https://gamepedia.cursecdn.com/dota2_ru_gamepedia/0/09/Dis_rival_19_ru.mp3"], "rattletrap \u0432\u0430\u0441 \u043a\u0430\u0440\u043b\u0438\u043a\u043e\u0432 \u0442\u0430\u043a \u043f\u0440\u0438\u044f\u0442\u043d\u043e \u0438\u0441\u0442\u0440\u0435\u0431\u043b\u044f\u0442\u044c": ["Disruptor", "https://gamepedia.cursecdn.com/dota2_ru_gamepedia/b/b5/Dis_rival_20_ru.mp3"], "\u043c\u0430\u0441\u0442\u0435\u0440\u0441\u0442\u0432\u0430 \u0442\u0435\u0431\u0435 \u043d\u0435 \u0437\u0430\u043d\u0438\u043c\u0430\u0442\u044c \u0430 \u043f\u0440\u043e\u0447\u043d\u043e\u0441\u0442\u044c \u043f\u043e\u0434\u0432\u0435\u043b\u0430": ["Disruptor", "https://gamepedia.cursecdn.com/dota2_ru_gamepedia/e/e1/Dis_rival_21_ru.mp3"], "gyro \u043d\u0435\u0443\u0436\u0435\u043b\u0438 \u0432 \u0442\u0432\u043e\u0451\u043c \u043f\u043b\u0435\u043c\u0435\u043d\u0438 \u0432\u0441\u0435 \u0442\u0430\u043a\u0438\u0435 \u043f\u0441\u0438\u0445\u0438": ["Disruptor", "https://gamepedia.cursecdn.com/dota2_ru_gamepedia/a/a0/Dis_rival_22_ru.mp3"], "gyro \u0442\u044b \u0434\u0430\u0436\u0435 \u043f\u043e\u0434\u043c\u0430\u0441\u0442\u0435\u0440\u044c\u0435\u0432 \u043d\u0435 \u043e\u0441\u0442\u0430\u0432\u0438\u043b": ["Disruptor", "https://gamepedia.cursecdn.com/dota2_ru_gamepedia/4/4d/Dis_rival_23_ru.mp3"], "\u0441\u043c\u043e\u0442\u0440\u0438 \u043f\u0440\u043e\u0441\u0442\u0443\u0434\u0438\u0448\u044c\u0441\u044f \u043d\u0430 \u0432\u0435\u0442\u0440\u0443": ["Disruptor", "https://gamepedia.cursecdn.com/dota2_ru_gamepedia/5/5d/Dis_rival_24_ru.mp3"], "\u0432\u043e\u0442 \u0442\u0430\u043a \u0438 \u043f\u043e\u0434\u043f\u0438\u0441\u044b\u0432\u0430\u044e\u0442 \u0441\u0435\u0431\u0435 \u043f\u0440\u0438\u0433\u043e\u0432\u043e\u0440": ["Disruptor", "https://gamepedia.cursecdn.com/dota2_ru_gamepedia/6/63/Dis_rival_25_ru.mp3"], "\u043d\u0435 \u0431\u0443\u0434\u0435\u0442 \u0431\u043e\u043b\u044c\u0448\u0435 \u043d\u0438 \u043a\u0430\u0440\u043b\u0438\u043a\u043e\u0432 \u043d\u0438 \u043e\u0433\u0440\u043e\u0432": ["Disruptor", "https://gamepedia.cursecdn.com/dota2_ru_gamepedia/5/50/Dis_rival_26_ru.mp3"], "\u0432 \u043f\u0440\u043e\u0433\u043d\u043e\u0437\u0435 \u043e\u0431\u0435\u0449\u0430\u043b\u0438 \u043f\u0435\u0440\u0432\u0443\u044e \u043a\u0440\u043e\u0432\u044c": ["Disruptor", "https://gamepedia.cursecdn.com/dota2_ru_gamepedia/5/53/Dis_first_01_ru.mp3"], "\u043c\u043e\u0439 \u0441\u043a\u0430\u043a\u0443\u043d \u043e\u0441\u0442\u0430\u0432\u043b\u044f\u0435\u0442 \u043a\u0440\u043e\u0432\u0430\u0432\u044b\u0435 \u0441\u043b\u0435\u0434\u044b": ["Disruptor", "https://gamepedia.cursecdn.com/dota2_ru_gamepedia/5/5c/Dis_first_02_ru.mp3"], "stryghor \u0441\u0442\u0443\u043f\u0430\u0435\u0442 \u043f\u043e \u043a\u0440\u043e\u0432\u0438": ["Disruptor", "https://gamepedia.cursecdn.com/dota2_ru_gamepedia/c/c9/Dis_first_03_ru.mp3"], "\u0434\u043e \u043f\u043e\u0441\u043b\u0435\u0434\u043d\u0435\u0439 \u043a\u0430\u043f\u043b\u0438 \u043a\u0440\u043e\u0432\u0438 stryghor": ["Disruptor", "https://gamepedia.cursecdn.com/dota2_ru_gamepedia/4/48/Dis_first_04_ru.mp3"], "razor \u0442\u044b \u043c\u043d\u0435 \u0434\u0440\u0443\u0433 \u043f\u043e\u043a\u0430 \u0433\u0440\u043e\u043c \u043d\u0435 \u0433\u0440\u044f\u043d\u0435\u0442": ["Disruptor", "https://gamepedia.cursecdn.com/dota2_ru_gamepedia/0/0d/Dis_ally_01_ru.mp3"], "\u0434\u0430 \u044d\u0442\u043e \u0436\u0435 zeus \u0432\u043b\u0430\u0434\u044b\u043a\u0430 \u0442\u0443\u0447": ["Disruptor", "https://gamepedia.cursecdn.com/dota2_ru_gamepedia/a/a3/Dis_ally_03_ru.mp3"], "\u0437\u0434\u0440\u0430\u0432\u0441\u0442\u0432\u0443\u0439 axe": ["Disruptor", "https://gamepedia.cursecdn.com/dota2_ru_gamepedia/9/9e/Dis_ally_05_ru.mp3"], "gyro \u043a\u0430\u043a \u0442\u0435\u0431\u0435 \u043f\u043e\u0433\u043e\u0434\u0430": ["Disruptor", "https://gamepedia.cursecdn.com/dota2_ru_gamepedia/9/92/Dis_ally_07_ru.mp3"], "storm spirit \u043c\u044b \u0441 \u0442\u043e\u0431\u043e\u0439 \u0441\u0440\u0430\u0431\u043e\u0442\u0430\u0435\u043c\u0441\u044f": ["Disruptor", "https://gamepedia.cursecdn.com/dota2_ru_gamepedia/3/34/Dis_ally_09_ru.mp3"], "razor \u043f\u043e\u0434\u0430\u0432\u0438\u043c \u0438\u0445 \u0441\u043e\u043f\u0440\u043e\u0442\u0438\u0432\u043b\u0435\u043d\u0438\u0435 \u0432\u043c\u0435\u0441\u0442\u0435": ["Disruptor", "https://gamepedia.cursecdn.com/dota2_ru_gamepedia/4/49/Dis_ally_02_ru.mp3"], "zeus \u0442\u044b \u0448\u0432\u044b\u0440\u044f\u0439 \u043c\u043e\u043b\u043d\u0438\u0438 \u0430 \u044f \u0443\u0441\u0442\u0440\u043e\u044e \u0433\u0440\u043e\u043c": ["Disruptor", "https://gamepedia.cursecdn.com/dota2_ru_gamepedia/4/44/Dis_ally_04_ru.mp3"], "\u043c\u043e\u0439 \u0441\u043e\u043f\u043b\u0435\u043c\u0435\u043d\u043d\u0438\u043a axe": ["Disruptor", "https://gamepedia.cursecdn.com/dota2_ru_gamepedia/6/6f/Dis_ally_06_ru.mp3"], "gyro \u0441\u0440\u0435\u0434\u0438 \u0442\u0432\u043e\u0438\u0445 \u0441\u043e\u0440\u043e\u0434\u0438\u0447\u0435\u0439 \u0431\u044b\u0432\u0430\u044e\u0442 \u0438 \u043f\u043e\u0445\u0443\u0436\u0435": ["Disruptor", "https://gamepedia.cursecdn.com/dota2_ru_gamepedia/4/46/Dis_ally_08_ru.mp3"], "\u043f\u043e\u0437\u043e\u043b\u043e\u0442\u0438\u043c \u044d\u043b\u0435\u043a\u0442\u0440\u043e\u0434\u044b": ["Disruptor", "https://gamepedia.cursecdn.com/dota2_ru_gamepedia/1/11/Dis_lasthit_01_ru.mp3"], "\u0441 \u0442\u043e\u0431\u043e\u0439 \u043f\u043e\u043a\u043e\u043d\u0447\u0435\u043d\u043e": ["Disruptor", "https://gamepedia.cursecdn.com/dota2_ru_gamepedia/7/74/Dis_lasthit_02_ru.mp3"], "\u0442\u0430\u043a\u043e\u0439 \u0448\u0430\u043d\u0441 \u0431\u044b\u0432\u0430\u0435\u0442 \u0440\u0430\u0437 \u0432 \u0436\u0438\u0437\u043d\u0438": ["Disruptor", "https://gamepedia.cursecdn.com/dota2_ru_gamepedia/8/8c/Dis_lasthit_04_ru.mp3"], "\u044d\u0442\u043e \u0442\u0435\u0431\u0435 \u0443\u0436\u0435 \u043d\u0438 \u043a \u0447\u0435\u043c\u0443": ["Disruptor", "https://gamepedia.cursecdn.com/dota2_ru_gamepedia/1/17/Dis_lasthit_05_ru.mp3"], "\u0436\u0438\u0437\u043d\u044c \u0437\u0430 \u0437\u043e\u043b\u043e\u0442\u043e": ["Disruptor", "https://gamepedia.cursecdn.com/dota2_ru_gamepedia/e/ed/Dis_lasthit_06_ru.mp3"], "\u0431\u044b\u0432\u0430\u0435\u0442 \u0438 \u0442\u0430\u043a": ["Disruptor", "https://gamepedia.cursecdn.com/dota2_ru_gamepedia/9/92/Dis_lasthit_07_ru.mp3"], "\u0447\u0442\u043e \u0437\u043d\u0430\u0447\u0438\u0442 \u0440\u0430\u0437\u0433\u0440\u043e\u043c": ["Disruptor", "https://gamepedia.cursecdn.com/dota2_ru_gamepedia/0/0e/Dis_lasthit_08_ru.mp3"], "\u043c\u043e\u043b\u043d\u0438\u0435\u043d\u043e\u0441\u043d\u043e": ["Disruptor", "https://gamepedia.cursecdn.com/dota2_ru_gamepedia/8/8e/Dis_lasthit_09_ru.mp3"], "\u0445\u0430\u0445": ["Disruptor", "https://gamepedia.cursecdn.com/dota2_ru_gamepedia/0/08/Dis_deny_01_ru.mp3"], "\u0432\u043e\u0442 \u0438 \u043d\u0435\u0442": ["Disruptor", "https://gamepedia.cursecdn.com/dota2_ru_gamepedia/e/e2/Dis_deny_02_ru.mp3"], "\u0432\u043e\u0442 \u0435\u0449\u0451": ["Disruptor", "https://gamepedia.cursecdn.com/dota2_ru_gamepedia/1/16/Dis_deny_03_ru.mp3"], "\u043d\u0435\u0442": ["Disruptor", "https://gamepedia.cursecdn.com/dota2_ru_gamepedia/2/22/Dis_lose_01_ru.mp3"], "\u043d\u0435 \u0443\u0441\u043f\u0435\u0435\u0448\u044c": ["Disruptor", "https://gamepedia.cursecdn.com/dota2_ru_gamepedia/5/59/Dis_deny_06_ru.mp3"], "\u043d\u0435 \u0441\u0443\u0434\u044c\u0431\u0430 \u0442\u0435\u0431\u0435": ["Disruptor", "https://gamepedia.cursecdn.com/dota2_ru_gamepedia/9/98/Dis_deny_07_ru.mp3"], "\u043d\u0435\u043b\u044c\u0437\u044f": ["Disruptor", "https://gamepedia.cursecdn.com/dota2_ru_gamepedia/a/a1/Dis_deny_13_ru.mp3"], "\u0445\u0435 \u0445\u0430 \u0445\u0430 \u0445\u0430 \u0445\u0430": ["Disruptor", "https://gamepedia.cursecdn.com/dota2_ru_gamepedia/6/67/Dis_deny_10_ru.mp3"], "\u0445\u0430 \u0445\u0430 \u0445\u0430 \u0430": ["Disruptor", "https://gamepedia.cursecdn.com/dota2_ru_gamepedia/b/b4/Dis_deny_11_ru.mp3"], "\u043a\u0445\u0430 \u0445\u0430 \u0445\u0430": ["Disruptor", "https://gamepedia.cursecdn.com/dota2_ru_gamepedia/5/5a/Dis_deny_12_ru.mp3"], "\u0442\u043e \u0447\u0442\u043e \u043d\u0443\u0436\u043d\u043e": ["Disruptor", "https://gamepedia.cursecdn.com/dota2_ru_gamepedia/2/2d/Dis_purch_01_ru.mp3"], "\u0443\u0434\u0430\u0447\u043d\u0430\u044f \u043f\u043e\u043a\u0443\u043f\u043a\u0430": ["Disruptor", "https://gamepedia.cursecdn.com/dota2_ru_gamepedia/e/ea/Dis_purch_02_ru.mp3"], "\u0441\u0442\u043e\u0438\u0442 \u0441\u0432\u043e\u0438\u0445 \u0434\u0435\u043d\u0435\u0433": ["Disruptor", "https://gamepedia.cursecdn.com/dota2_ru_gamepedia/1/17/Dis_purch_03_ru.mp3"], "\u0430\u0445 \u0441\u043a\u0438\u043f\u0435\u0442\u0440": ["Disruptor", "https://gamepedia.cursecdn.com/dota2_ru_gamepedia/f/fe/Dis_scepter_01_ru.mp3"], "\u0445\u043e\u0434 \u0431\u043e\u044f \u043f\u0435\u0440\u0435\u043b\u043e\u043c\u043b\u0435\u043d": ["Disruptor", "https://gamepedia.cursecdn.com/dota2_ru_gamepedia/2/20/Dis_scepter_02_ru.mp3"], "blink dagger": ["Disruptor", "https://gamepedia.cursecdn.com/dota2_ru_gamepedia/6/6b/Dis_blink_01_ru.mp3"], "\u0438 \u043c\u043e\u0436\u043d\u043e \u043d\u0430\u043f\u0430\u0434\u0430\u0442\u044c": ["Disruptor", "https://gamepedia.cursecdn.com/dota2_ru_gamepedia/a/a6/Dis_blink_02_ru.mp3"], "mekansm": ["Disruptor", "https://gamepedia.cursecdn.com/dota2_ru_gamepedia/d/dc/Dis_items_01_ru.mp3"], "scepter of divinity": ["Disruptor", "https://gamepedia.cursecdn.com/dota2_ru_gamepedia/2/2f/Dis_items_02_ru.mp3"], "force staff": ["Disruptor", "https://gamepedia.cursecdn.com/dota2_ru_gamepedia/4/49/Dis_items_03_ru.mp3"], "linken s sphere": ["Disruptor", "https://gamepedia.cursecdn.com/dota2_ru_gamepedia/2/28/Dis_items_04_ru.mp3"], "scythe of vyse": ["Disruptor", "https://gamepedia.cursecdn.com/dota2_ru_gamepedia/9/99/Dis_items_05_ru.mp3"], "necronomicon": ["Disruptor", "https://gamepedia.cursecdn.com/dota2_ru_gamepedia/d/df/Dis_items_06_ru.mp3"], "pipe": ["Disruptor", "https://gamepedia.cursecdn.com/dota2_ru_gamepedia/c/cd/Dis_items_07_ru.mp3"], "pipe of insight": ["Disruptor", "https://gamepedia.cursecdn.com/dota2_ru_gamepedia/3/3a/Dis_items_11_ru.mp3"], "shiva s guard": ["Disruptor", "https://gamepedia.cursecdn.com/dota2_ru_gamepedia/e/e7/Dis_items_08_ru.mp3"], "vanguard": ["Disruptor", "https://gamepedia.cursecdn.com/dota2_ru_gamepedia/5/50/Dis_items_09_ru.mp3"], "dagon": ["Disruptor", "https://gamepedia.cursecdn.com/dota2_ru_gamepedia/7/7b/Dis_items_10_ru.mp3"], "veil of discord": ["Disruptor", "https://gamepedia.cursecdn.com/dota2_ru_gamepedia/5/56/Dis_items_12_ru.mp3"], "\u0431\u0435\u0441\u0441\u043c\u0435\u0440\u0442\u0438\u0435": ["Disruptor", "https://gamepedia.cursecdn.com/dota2_ru_gamepedia/9/9c/Dis_immort_01_ru.mp3"], "\u0447\u0442\u043e \u043c\u043e\u0436\u0435\u0442 \u0431\u044b\u0442\u044c \u043b\u0443\u0447\u0448\u0435 \u0434\u043e\u043b\u0433\u043e\u043b\u0435\u0442\u0438\u044f": ["Disruptor", "https://gamepedia.cursecdn.com/dota2_ru_gamepedia/0/00/Dis_immort_02_ru.mp3"], "\u0437\u0430\u0447\u0435\u043c": ["Disruptor", "https://gamepedia.cursecdn.com/dota2_ru_gamepedia/c/c1/Dis_death_03_ru.mp3"], "\u043e \u043d\u0435\u0442 \u043e\u0445": ["Disruptor", "https://gamepedia.cursecdn.com/dota2_ru_gamepedia/c/c2/Dis_death_04_ru.mp3"], "\u043c\u043e\u044f \u0436\u0438\u0437\u043d\u044c \u043f\u0440\u043e\u043f\u0430\u043b\u0430 \u0437\u0440\u044f": ["Disruptor", "https://gamepedia.cursecdn.com/dota2_ru_gamepedia/0/03/Dis_death_05_ru.mp3"], "\u043f\u043e\u0445\u043e\u0440\u043e\u043d\u0438\u0442\u0435 \u043c\u0435\u043d\u044f \u0432 \u0440\u043e\u0434\u043d\u044b\u0445 \u0441\u0442\u0435\u043f\u044f\u0445": ["Disruptor", "https://gamepedia.cursecdn.com/dota2_ru_gamepedia/3/35/Dis_death_06_ru.mp3"], "\u044f \u0432\u043e\u0437\u0432\u0440\u0430\u0449\u0430\u044e\u0441\u044c \u043d\u0430 \u0440\u043e\u0434\u0438\u043d\u0443 \u043f\u0440\u0435\u0434\u043a\u043e\u0432": ["Disruptor", "https://gamepedia.cursecdn.com/dota2_ru_gamepedia/d/d0/Dis_death_07_ru.mp3"], "\u043c\u043e\u0439 \u0437\u0430\u0440\u044f\u0434 \u0438\u0441\u0447\u0435\u0440\u043f\u0430\u043d": ["Disruptor", "https://gamepedia.cursecdn.com/dota2_ru_gamepedia/2/2e/Dis_death_08_ru.mp3"], "\u044f \u0441\u043e\u0432\u0441\u0435\u043c \u0440\u0430\u0437\u0440\u044f\u0436\u0435\u043d": ["Disruptor", "https://gamepedia.cursecdn.com/dota2_ru_gamepedia/d/dc/Dis_death_09_ru.mp3"], "\u044f \u043e\u0442\u043a\u043b\u044e\u0447\u0430\u044e\u0441\u044c \u0438 \u0433\u0430\u0441\u043d\u0443": ["Disruptor", "https://gamepedia.cursecdn.com/dota2_ru_gamepedia/d/d8/Dis_death_10_ru.mp3"], "\u0447\u0442\u043e \u0442\u0430\u043a\u043e\u0435 \u043c\u0435\u043d\u044f \u0443\u0431\u0438\u043b\u0438": ["Disruptor", "https://gamepedia.cursecdn.com/dota2_ru_gamepedia/2/2a/Dis_death_11_ru.mp3"], "\u0432\u043e\u0442 \u0438 \u044f \u043f\u043e\u0436\u0438\u043d\u0430\u044e \u0431\u0443\u0440\u044e": ["Disruptor", "https://gamepedia.cursecdn.com/dota2_ru_gamepedia/a/ac/Dis_death_12_ru.mp3"], "\u0437\u0430\u0442\u0443\u043c\u0430\u043d\u0438\u043b\u043e\u0441\u044c \u043c\u043e\u0451 \u043d\u0435\u0431\u043e": ["Disruptor", "https://gamepedia.cursecdn.com/dota2_ru_gamepedia/f/f8/Dis_death_13_ru.mp3"], "\u0437\u043d\u0430\u043d\u0438\u044f \u0441\u043d\u043e\u0432\u0430 \u0443\u043c\u0440\u0443\u0442 \u0441\u043e \u043c\u043d\u043e\u0439": ["Disruptor", "https://gamepedia.cursecdn.com/dota2_ru_gamepedia/c/cf/Dis_death_14_ru.mp3"], "\u043f\u0440\u0435\u0434\u0432\u0435\u0447\u043d\u044b\u0435 \u0441\u0442\u0435\u043f\u0438": ["Disruptor", "https://gamepedia.cursecdn.com/dota2_ru_gamepedia/a/aa/Dis_death_15_ru.mp3"], "\u044f \u0432\u043d\u043e\u0432\u044c \u043d\u0430 \u043a\u043e\u043d\u0435": ["Disruptor", "https://gamepedia.cursecdn.com/dota2_ru_gamepedia/8/8d/Dis_respawn_01_ru.mp3"], "\u0432\u043f\u0435\u0440\u0451\u0434 \u043c\u043e\u0439 \u0441\u043a\u0430\u043a\u0443\u043d": ["Disruptor", "https://gamepedia.cursecdn.com/dota2_ru_gamepedia/3/3e/Dis_respawn_02_ru.mp3"], "\u0432\u043e\u0437\u0432\u0440\u0430\u0449\u0430\u044e\u0441\u044c \u0432 \u0431\u043e\u0439": ["Disruptor", "https://gamepedia.cursecdn.com/dota2_ru_gamepedia/c/c6/Dis_respawn_03_ru.mp3"], "\u044f \u0441\u043d\u043e\u0432\u0430 \u043f\u043e\u043b\u043d\u043e\u0441\u0442\u044c\u044e \u0437\u0430\u0440\u044f\u0436\u0435\u043d": ["Disruptor", "https://gamepedia.cursecdn.com/dota2_ru_gamepedia/c/cd/Dis_respawn_04_ru.mp3"], "\u0431\u0443\u0440\u044f \u0437\u0430\u0440\u044f\u0434\u0438\u043b\u0430 \u043c\u0435\u043d\u044f": ["Disruptor", "https://gamepedia.cursecdn.com/dota2_ru_gamepedia/a/ab/Dis_respawn_05_ru.mp3"], "\u043f\u043e\u0437\u043e\u0440 \u0434\u043e\u043b\u0436\u0435\u043d \u0431\u044b\u0442\u044c \u0441\u043c\u044b\u0442": ["Disruptor", "https://gamepedia.cursecdn.com/dota2_ru_gamepedia/c/cd/Dis_respawn_06_ru.mp3"], "\u043c\u043e\u044f \u043c\u0435\u0441\u0442\u044c \u0432\u043e\u0439\u0434\u0451\u0442 \u0432 \u043b\u0435\u0433\u0435\u043d\u0434\u044b": ["Disruptor", "https://gamepedia.cursecdn.com/dota2_ru_gamepedia/2/26/Dis_respawn_07_ru.mp3"], "\u043f\u043e\u0449\u0430\u0434\u044b \u043d\u0435 \u0431\u0443\u0434\u0435\u0442": ["Disruptor", "https://gamepedia.cursecdn.com/dota2_ru_gamepedia/3/38/Dis_respawn_08_ru.mp3"], "\u0438\u0441\u043a\u0440\u044e\u0441\u044c \u0436\u0438\u0437\u043d\u044c\u044e": ["Disruptor", "https://gamepedia.cursecdn.com/dota2_ru_gamepedia/e/e6/Dis_respawn_09_ru.mp3"], "\u043f\u043b\u0435\u043c\u044f \u043f\u0430\u0432\u0448\u0438\u0445 \u0432\u043e\u0437\u0440\u043e\u0436\u0434\u0430\u0435\u0442\u0441\u044f": ["Disruptor", "https://gamepedia.cursecdn.com/dota2_ru_gamepedia/3/3f/Dis_respawn_11_ru.mp3"], "\u043a\u0442\u043e \u0440\u0430\u0437\u043e\u0433\u043d\u0430\u043b \u043d\u0430\u0434\u043e \u043c\u043d\u043e\u044e \u0442\u0443\u0447\u0438": ["Disruptor", "https://gamepedia.cursecdn.com/dota2_ru_gamepedia/1/17/Dis_respawn_12_ru.mp3"], "\u043a\u0442\u043e \u0442\u0443\u0442 \u0443\u043f\u0440\u0430\u0432\u043b\u044f\u0435\u0442 \u043f\u043e\u0433\u043e\u0434\u043e\u0439": ["Disruptor", "https://gamepedia.cursecdn.com/dota2_ru_gamepedia/6/64/Dis_respawn_10_ru.mp3"], "\u0431\u0443\u0440\u044f \u043f\u0440\u0438\u043d\u0435\u0441\u043b\u0430 \u043c\u0435\u043d\u044f \u043e\u0431\u0440\u0430\u0442\u043d\u043e": ["Disruptor", "https://gamepedia.cursecdn.com/dota2_ru_gamepedia/4/49/Dis_fastres_01_ru.mp3"], "\u043d\u0430 \u043f\u043e\u0442\u043e\u043c": ["Disruptor", "https://gamepedia.cursecdn.com/dota2_ru_gamepedia/c/c7/Dis_bottle_01_ru.mp3"], "\u043a\u043e\u0433\u0434\u0430 \u043d\u0438\u0431\u0443\u0434\u044c \u043f\u0440\u0438\u0433\u043e\u0434\u0438\u0442\u0441\u044f": ["Disruptor", "https://gamepedia.cursecdn.com/dota2_ru_gamepedia/7/70/Dis_bottle_02_ru.mp3"], "\u0432 \u0431\u0443\u0442\u044b\u043b\u044c": ["Disruptor", "https://gamepedia.cursecdn.com/dota2_ru_gamepedia/6/6f/Dis_bottle_03_ru.mp3"], "\u0431\u0438\u0442\u0432\u0430 \u043e\u0442\u0433\u0440\u0435\u043c\u0435\u043b\u0430 \u043d\u0435 \u043d\u0430\u043f\u0440\u0430\u0441\u043d\u043e": ["Disruptor", "https://gamepedia.cursecdn.com/dota2_ru_gamepedia/0/0c/Dis_itemmoderate_01_ru.mp3"], "\u0434\u0432\u043e\u0439\u043d\u043e\u0439 \u0443\u0440\u043e\u043d": ["Disruptor", "https://gamepedia.cursecdn.com/dota2_ru_gamepedia/b/b1/Dis_doubdam_01_ru.mp3"], "\u0434\u0432\u043e\u0439\u043d\u043e\u0439 \u0443\u0434\u0430\u0440": ["Disruptor", "https://gamepedia.cursecdn.com/dota2_ru_gamepedia/0/01/Dis_doubdam_02_ru.mp3"], "\u0443\u0441\u043a\u043e\u0440\u0435\u043d\u0438\u0435": ["Disruptor", "https://gamepedia.cursecdn.com/dota2_ru_gamepedia/a/a8/Dis_haste_01_ru.mp3"], "\u0431\u0443\u0434\u0435\u043c \u043f\u043e\u0441\u043f\u0435\u0448\u043d\u044b": ["Disruptor", "https://gamepedia.cursecdn.com/dota2_ru_gamepedia/9/97/Dis_haste_02_ru.mp3"], "stryghor \u0431\u0443\u0434\u0435\u0442 \u0441\u0442\u0440\u0435\u043c\u0438\u0442\u0435\u043b\u0435\u043d": ["Disruptor", "https://gamepedia.cursecdn.com/dota2_ru_gamepedia/7/79/Dis_haste_03_ru.mp3"], "\u0438\u043b\u043b\u044e\u0437\u0438\u044f": ["Disruptor", "https://gamepedia.cursecdn.com/dota2_ru_gamepedia/1/13/Dis_illus_01_ru.mp3"], "\u0437\u0430\u043d\u044f\u0442\u043d\u043e\u0435 \u0437\u0440\u0435\u043b\u0438\u0449\u0435": ["Disruptor", "https://gamepedia.cursecdn.com/dota2_ru_gamepedia/b/be/Dis_illus_02_ru.mp3"], "\u043d\u0435\u0432\u0438\u0434\u0438\u043c\u043e\u0441\u0442\u044c": ["Disruptor", "https://gamepedia.cursecdn.com/dota2_ru_gamepedia/2/24/Dis_invis_01_ru.mp3"], "\u043a\u0430\u043a \u0433\u0440\u043e\u043c \u0441\u0440\u0435\u0434\u0438 \u044f\u0441\u043d\u043e\u0433\u043e \u043d\u0435\u0431\u0430": ["Disruptor", "https://gamepedia.cursecdn.com/dota2_ru_gamepedia/c/cf/Dis_invis_02_ru.mp3"], "\u0440\u0435\u0433\u0435\u043d\u0435\u0440\u0430\u0446\u0438\u044f": ["Disruptor", "https://gamepedia.cursecdn.com/dota2_ru_gamepedia/9/98/Dis_regen_01_ru.mp3"], "\u0445\u0430 \u044f \u0447\u0443\u0432\u0441\u0442\u0432\u0443\u044e \u0441\u0435\u0431\u044f \u043d\u0430\u043c\u043d\u043e\u0433\u043e \u043b\u0443\u0447\u0448\u0435": ["Disruptor", "https://gamepedia.cursecdn.com/dota2_ru_gamepedia/1/12/Dis_regen_02_ru.mp3"], "\u043d\u0435 \u0441\u0435\u0439\u0447\u0430\u0441": ["Disruptor", "https://gamepedia.cursecdn.com/dota2_ru_gamepedia/d/d1/Dis_notyet_03_ru.mp3"], "\u044f \u043d\u0435 \u0433\u043e\u0442\u043e\u0432": ["Disruptor", "https://gamepedia.cursecdn.com/dota2_ru_gamepedia/b/b2/Dis_notyet_06_ru.mp3"], "\u0435\u0449\u0451 \u0441\u043b\u0438\u0448\u043a\u043e\u043c \u0440\u0430\u043d\u043e": ["Disruptor", "https://gamepedia.cursecdn.com/dota2_ru_gamepedia/6/67/Dis_notyet_09_ru.mp3"], "\u043c\u0430\u043d\u044b \u043d\u0435\u0442": ["Disruptor", "https://gamepedia.cursecdn.com/dota2_ru_gamepedia/9/9f/Dis_nomana_03_ru.mp3"], "\u043d\u0435\u0442 \u043c\u0430\u043d\u044b": ["Disruptor", "https://gamepedia.cursecdn.com/dota2_ru_gamepedia/8/84/Dis_nomana_06_ru.mp3"], "\u043d\u0435\u0434\u043e\u0441\u0442\u0430\u0442\u043e\u0447\u043d\u043e \u043c\u0430\u043d\u044b": ["Disruptor", "https://gamepedia.cursecdn.com/dota2_ru_gamepedia/7/7e/Dis_nomana_08_ru.mp3"], "\u0443 \u0448": ["Disruptor", "https://gamepedia.cursecdn.com/dota2_ru_gamepedia/5/55/Dis_pain_01_ru.mp3"], "\u0430\u0445": ["Disruptor", "https://gamepedia.cursecdn.com/dota2_ru_gamepedia/8/84/Dis_happy_07_ru.mp3"], "\u0443\u043c": ["Disruptor", "https://gamepedia.cursecdn.com/dota2_ru_gamepedia/0/04/Dis_pain_03_ru.mp3"], "\u043e\u0443": ["Disruptor", "https://gamepedia.cursecdn.com/dota2_ru_gamepedia/6/62/Dis_pain_09_ru.mp3"], "\u0430\u0440 \u0445": ["Disruptor", "https://gamepedia.cursecdn.com/dota2_ru_gamepedia/c/c9/Dis_pain_05_ru.mp3"], "\u0443 \u0443": ["Disruptor", "https://gamepedia.cursecdn.com/dota2_ru_gamepedia/f/f0/Dis_pain_06_ru.mp3"], "\u0443\u0433\u0445": ["Disruptor", "https://gamepedia.cursecdn.com/dota2_ru_gamepedia/9/95/Dis_pain_07_ru.mp3"], "\u044d \u044d": ["Disruptor", "https://gamepedia.cursecdn.com/dota2_ru_gamepedia/2/24/Dis_pain_10_ru.mp3"], "\u0430 \u0430\u0443": ["Disruptor", "https://gamepedia.cursecdn.com/dota2_ru_gamepedia/a/a7/Dis_pain_11_ru.mp3"], "\u043d\u0430 \u043c\u0435\u043d\u044f \u043d\u0430\u043f\u0430\u043b\u0438": ["Disruptor", "https://gamepedia.cursecdn.com/dota2_ru_gamepedia/e/e3/Dis_underattack_01_ru.mp3"], "\u043c\u0435\u043d\u044f \u043f\u044b\u0442\u0430\u044e\u0442\u0441\u044f \u0443\u0431\u0438\u0442\u044c": ["Disruptor", "https://gamepedia.cursecdn.com/dota2_ru_gamepedia/4/4c/Dis_underattack_02_ru.mp3"], "\u0433\u0440\u043e\u043c\u043e\u0432\u0435\u0440\u0436\u0435\u0446 \u0432\u043e\u0442 \u043a\u0442\u043e \u044f": ["Disruptor", "https://gamepedia.cursecdn.com/dota2_ru_gamepedia/a/ae/Dis_rare_02_ru.mp3"], "\u0433\u0440\u043e\u043c\u044b \u0438 \u043c\u043e\u043b\u043d\u0438\u0438 \u043f\u043e\u0434\u0432\u043b\u0430\u0441\u0442\u043d\u044b \u043c\u043e\u0435\u043c\u0443 \u0441\u043b\u043e\u0432\u0443": ["Disruptor", "https://gamepedia.cursecdn.com/dota2_ru_gamepedia/2/21/Dis_rare_03_ru.mp3"], "\u043d\u0430\u0432\u0435\u0440\u0445\u0443 \u043d\u0438\u043a\u043e\u0433\u043e": ["Disruptor", "https://gamepedia.cursecdn.com/dota2_ru_gamepedia/4/4c/Dis_lane_missing_01_ru.mp3"], "\u0432 \u0446\u0435\u043d\u0442\u0440\u0435 \u043d\u0438\u043a\u043e\u0433\u043e": ["Disruptor", "https://gamepedia.cursecdn.com/dota2_ru_gamepedia/2/2b/Dis_lane_missing_02_ru.mp3"], "\u0432\u043d\u0438\u0437\u0443 \u043d\u0438\u043a\u043e\u0433\u043e": ["Disruptor", "https://gamepedia.cursecdn.com/dota2_ru_gamepedia/4/4d/Dis_lane_missing_03_ru.mp3"], "\u0441\u043f\u0430\u0441\u0438\u0431\u043e": ["Disruptor", "https://gamepedia.cursecdn.com/dota2_ru_gamepedia/7/75/Dis_thanks_01_ru.mp3"], "\u0431\u043b\u0430\u0433\u043e\u0434\u0430\u0440\u044e": ["Disruptor", "https://gamepedia.cursecdn.com/dota2_ru_gamepedia/7/72/Dis_thanks_02_ru.mp3"], "\u0432\u0435\u0441\u044c\u043c\u0430 \u0431\u043b\u0430\u0433\u043e\u0434\u0430\u0440\u0435\u043d": ["Disruptor", "https://gamepedia.cursecdn.com/dota2_ru_gamepedia/8/8b/Dis_thanks_03_ru.mp3"], "\u044f \u044d\u0442\u043e \u0446\u0435\u043d\u044e": ["Disruptor", "https://gamepedia.cursecdn.com/dota2_ru_gamepedia/2/2c/Dis_thanks_04_ru.mp3"], "\u043e\u0447\u0435\u043d\u044c \u043f\u0440\u0438\u0437\u043d\u0430\u0442\u0435\u043b\u0435\u043d": ["Disruptor", "https://gamepedia.cursecdn.com/dota2_ru_gamepedia/8/83/Dis_thanks_06_ru.mp3"], "\u043f\u0440\u0435\u043c\u043d\u043e\u0433\u043e \u0431\u043b\u0430\u0433\u043e\u0434\u0430\u0440\u0435\u043d": ["Disruptor", "https://gamepedia.cursecdn.com/dota2_ru_gamepedia/9/93/Dis_thanks_07_ru.mp3"], "\u0431\u043e\u043b\u044c\u0448\u043e\u0435 \u0441\u043f\u0430\u0441\u0438\u0431\u043e": ["Disruptor", "https://gamepedia.cursecdn.com/dota2_ru_gamepedia/5/52/Dis_thanks_08_ru.mp3"], "\u0445\u0435": ["Disruptor", "https://gamepedia.cursecdn.com/dota2_ru_gamepedia/a/a5/Dis_laugh_01_ru.mp3"], "\u043e\u0445 \u0445\u043e\u0445": ["Disruptor", "https://gamepedia.cursecdn.com/dota2_ru_gamepedia/7/7c/Dis_laugh_02_ru.mp3"], "\u0445\u0435 \u0445\u0430 \u0445\u0430": ["Disruptor", "https://gamepedia.cursecdn.com/dota2_ru_gamepedia/0/07/Dis_laugh_03_ru.mp3"], "\u0445\u0430 \u0445\u0430 \u0445\u0430 \u0445\u0430 \u0430 \u0445\u0430 \u0430 \u0445\u0430 \u0445\u0430": ["Disruptor", "https://gamepedia.cursecdn.com/dota2_ru_gamepedia/b/be/Dis_laugh_06_ru.mp3"], "\u043e\u0443 \u043a\u0445\u043e \u043a\u0445\u0430 \u0445\u0430 \u0445\u0430 \u0445\u0430": ["Disruptor", "https://gamepedia.cursecdn.com/dota2_ru_gamepedia/5/53/Dis_laugh_07_ru.mp3"], "\u0443\u0440\u0430": ["Disruptor", "https://gamepedia.cursecdn.com/dota2_ru_gamepedia/4/48/Dis_win_01_ru.mp3"], "\u043f\u043e\u0431\u0435\u0434\u0430": ["Disruptor", "https://gamepedia.cursecdn.com/dota2_ru_gamepedia/d/df/Dis_win_02_ru.mp3"], "\u043d\u0430\u043c \u043e\u0431\u0435\u0449\u0430\u044e\u0442 \u044f\u0441\u043d\u0443\u044e \u043f\u043e\u0433\u043e\u0434\u0443": ["Disruptor", "https://gamepedia.cursecdn.com/dota2_ru_gamepedia/d/d9/Dis_win_04_ru.mp3"], "\u043c\u044b \u043f\u043e\u0431\u0435\u0434\u0438\u043b\u0438 \u043f\u0440\u043e\u0433\u043d\u043e\u0437 \u0441\u0431\u044b\u043b\u0441\u044f": ["Disruptor", "https://gamepedia.cursecdn.com/dota2_ru_gamepedia/4/4d/Dis_win_05_ru.mp3"], "\u044f \u043f\u0440\u043e\u0438\u0433\u0440\u0430\u043b": ["Disruptor", "https://gamepedia.cursecdn.com/dota2_ru_gamepedia/1/17/Dis_lose_02_ru.mp3"], "\u0438\u0441\u043f\u043e\u0440\u0442\u0438\u043b\u0438 \u043c\u043d\u0435 \u0441\u0435\u0440\u0434\u0435\u0447\u043d\u0438\u043a": ["Disruptor", "https://gamepedia.cursecdn.com/dota2_ru_gamepedia/c/c8/Dis_lose_04_ru.mp3"], "\u044f \u0443\u043d\u0435\u0441\u0443 \u0437\u043d\u0430\u043d\u0438\u044f \u0432 \u043c\u043e\u0433\u0438\u043b\u0443": ["Disruptor", "https://gamepedia.cursecdn.com/dota2_ru_gamepedia/c/ca/Dis_lose_05_ru.mp3"], "\u043c\u0435\u0442\u0435\u043e\u0440\u043e\u043b\u043e\u0433\u0438 \u043e\u043f\u044f\u0442\u044c \u043e\u0448\u0438\u0431\u043b\u0438\u0441\u044c": ["Disruptor", "https://gamepedia.cursecdn.com/dota2_ru_gamepedia/d/d0/Dis_lose_06_ru.mp3"], "\u0433\u0440\u043e\u0437\u0430 \u043f\u0440\u0438\u043d\u0435\u0441\u043b\u0430 \u043a\u043e\u0435 \u0447\u0442\u043e \u043f\u043e\u043b\u0435\u0437\u043d\u043e\u0435": ["Disruptor", "https://gamepedia.cursecdn.com/dota2_ru_gamepedia/b/b9/Dis_itemcommon_01_ru.mp3"], "\u043e\u0445 \u043a\u0430\u043a\u0438\u0435 \u0431\u0443\u0440\u0438 \u044f \u0442\u0435\u043f\u0435\u0440\u044c \u0443\u0441\u0442\u0440\u043e\u044e": ["Disruptor", "https://gamepedia.cursecdn.com/dota2_ru_gamepedia/2/2f/Dis_itemrare_01_ru.mp3"], "\u043c\u0438\u043c\u043e": ["Disruptor", "https://gamepedia.cursecdn.com/dota2_ru_gamepedia/2/29/Dis_failure_02_ru.mp3"], "\u0442\u044c\u0444\u0443": ["Disruptor", "https://gamepedia.cursecdn.com/dota2_ru_gamepedia/3/38/Dis_failure_06_ru.mp3"], "\u043a\u0430\u043a \u0436\u0435 \u0442\u0430\u043a": ["Disruptor", "https://gamepedia.cursecdn.com/dota2_ru_gamepedia/2/22/Dis_failure_04_ru.mp3"], "\u043e\u0445 \u043d\u0435 \u043f\u043e\u043f\u0430\u043b": ["Disruptor", "https://gamepedia.cursecdn.com/dota2_ru_gamepedia/8/81/Dis_failure_05_ru.mp3"], "\u043e\u0445": ["Disruptor", "https://gamepedia.cursecdn.com/dota2_ru_gamepedia/3/36/Dis_failure_07_ru.mp3"], "\u0438\u0448\u044c \u043f\u043e\u0447\u0442\u0438 \u043f\u043e\u043f\u0430\u043b": ["Disruptor", "https://gamepedia.cursecdn.com/dota2_ru_gamepedia/0/07/Dis_failure_08_ru.mp3"], "\u043f\u0430\u0440\u0448\u0438\u0432\u044b\u0439 \u0432\u043e\u043b\u0448\u0435\u0431\u043d\u0438\u043a": ["Disruptor", "https://gamepedia.cursecdn.com/dota2_ru_gamepedia/b/b8/Dis_crumwiz_01_ru.mp3"], "\u043e \u043e \u0445": ["Disruptor", "https://gamepedia.cursecdn.com/dota2_ru_gamepedia/3/31/Dis_anger_01_ru.mp3"], "\u043a \u0445\u0430": ["Disruptor", "https://gamepedia.cursecdn.com/dota2_ru_gamepedia/8/83/Dis_anger_05_ru.mp3"], "\u043c\u0435 \u0435": ["Disruptor", "https://gamepedia.cursecdn.com/dota2_ru_gamepedia/a/aa/Dis_anger_04_ru.mp3"], "\u043c \u043c\u0435 \u0433\u0445": ["Disruptor", "https://gamepedia.cursecdn.com/dota2_ru_gamepedia/d/d0/Dis_anger_06_ru.mp3"], "\u0430 \u0430 \u0430\u043e": ["Disruptor", "https://gamepedia.cursecdn.com/dota2_ru_gamepedia/e/e7/Dis_anger_07_ru.mp3"], "\u0435 \u0440\u0445": ["Disruptor", "https://gamepedia.cursecdn.com/dota2_ru_gamepedia/f/f2/Dis_anger_08_ru.mp3"], "\u0430 \u0430": ["Disruptor", "https://gamepedia.cursecdn.com/dota2_ru_gamepedia/d/d6/Dis_anger_09_ru.mp3"], "\u0434\u043e \u043e\u0440\u0445": ["Disruptor", "https://gamepedia.cursecdn.com/dota2_ru_gamepedia/e/e1/Dis_anger_10_ru.mp3"], "\u0440 \u044b\u0430": ["Disruptor", "https://gamepedia.cursecdn.com/dota2_ru_gamepedia/e/e9/Dis_anger_11_ru.mp3"], "\u043c \u043c": ["Disruptor", "https://gamepedia.cursecdn.com/dota2_ru_gamepedia/2/28/Dis_happy_01_ru.mp3"], "\u043e \u043e\u0445": ["Disruptor", "https://gamepedia.cursecdn.com/dota2_ru_gamepedia/7/73/Dis_happy_02_ru.mp3"], "\u043c \u043c \u0445\u043c": ["Disruptor", "https://gamepedia.cursecdn.com/dota2_ru_gamepedia/3/3d/Dis_happy_03_ru.mp3"], "\u0443 \u0443\u043c": ["Disruptor", "https://gamepedia.cursecdn.com/dota2_ru_gamepedia/6/6a/Dis_happy_04_ru.mp3"], "\u043e \u043e": ["Disruptor", "https://gamepedia.cursecdn.com/dota2_ru_gamepedia/1/12/Dis_happy_05_ru.mp3"], "\u043e \u0445\u043e \u0445\u043e \u0445\u043e": ["Disruptor", "https://gamepedia.cursecdn.com/dota2_ru_gamepedia/3/3e/Dis_happy_06_ru.mp3"], "\u0445\u0430 \u0430\u0445": ["Disruptor", "https://gamepedia.cursecdn.com/dota2_ru_gamepedia/1/1d/Dis_happy_08_ru.mp3"], "\u0430 \u0430\u0445": ["Disruptor", "https://gamepedia.cursecdn.com/dota2_ru_gamepedia/c/c9/Dis_happy_09_ru.mp3"], "\u0430 \u0430 \u0445": ["Disruptor", "https://gamepedia.cursecdn.com/dota2_ru_gamepedia/b/bb/Dis_happy_10_ru.mp3"], "\u0443 \u0443 \u0434\u0430": ["Disruptor", "https://gamepedia.cursecdn.com/dota2_ru_gamepedia/8/86/Dis_unknown_01_ru.mp3"]}